graphiit/__init__.py
graphiit/graph.py
graphiit/micro_mechanisms.py
graphiit/utils.py
graphiit-0.1.0.dist-info/METADATA
graphiit-0.1.0.dist-info/RECORD
graphiit-0.1.0.dist-info/WHEEL
graphiit-0.1.0.dist-info/top_level.txt
