Metadata-Version: 2.1
Name: graphiit
Version: 0.1.0
Summary: Python library for building PyPhi network graphs
Home-page: http://github.com/grahamfindlay/graphiit
Author: Graham Findlay
Author-email: UNKNOWN
License: GNU General Public License v3.0
Platform: UNKNOWN
Classifier: Development Status :: 3 - Alpha
Classifier: Intended Audience :: Developers
Classifier: Natural Language :: English
Classifier: License :: OSI Approved :: GNU General Public License v3 or later (GPLv3+)
Classifier: Programming Language :: Python
Classifier: Programming Language :: Python :: 3
Classifier: Topic :: Scientific/Engineering
Requires-Dist: numpy
Requires-Dist: pyphi (>=1.0.0)
Requires-Dist: networkx (<2.0.0)
